remecap/__init__.py
remecap/indirect.py
remecap/solver.py
remecap/yolov5/__init__.py
remecap/yolov5/yolov5.py
remecap/yolov5/models/coco128.yaml
remecap/yolov5/models/common.py
remecap/yolov5/models/experimental.py
remecap/yolov5/models/yolo.py
remecap/yolov5/utils/activations.py
remecap/yolov5/utils/augmentations.py
remecap/yolov5/utils/autoanchor.py
remecap/yolov5/utils/autobatch.py
remecap/yolov5/utils/callbacks.py
remecap/yolov5/utils/datasets.py
remecap/yolov5/utils/downloads.py
remecap/yolov5/utils/general.py
remecap/yolov5/utils/loss.py
remecap/yolov5/utils/metrics.py
remecap/yolov5/utils/plots.py
remecap/yolov5/utils/torch_utils.py
remecap-1.5.0.dist-info/LICENSE
remecap-1.5.0.dist-info/METADATA
remecap-1.5.0.dist-info/WHEEL
remecap-1.5.0.dist-info/top_level.txt
remecap-1.5.0.dist-info/RECORD
